aiothrottles/__init__.py
aiothrottles/throttles.py
aiothrottles-0.2.0.dist-info/LICENSE
aiothrottles-0.2.0.dist-info/METADATA
aiothrottles-0.2.0.dist-info/WHEEL
aiothrottles-0.2.0.dist-info/top_level.txt
aiothrottles-0.2.0.dist-info/RECORD
