Metadata-Version: 2.1
Name: aiothrottles
Version: 0.2.0
Summary: Throttles for Python coroutines.
Home-page: https://github.com/KonstantinTogoi/aiothrottles
Download-URL: https://pypi.org/project/aiothrottles/
Author: Konstantin Togoi
Author-email: konstantin.togoi@gmail.com
License: BSD
Project-URL: Documentation, https://konstantintogoi.github.io/aiothrottles
Keywords: asyncio synchronization lock semaphorethrottler throttles throttling rate limiting
Platform: Any
Classifier: Intended Audience :: Developers
Classifier: License :: OSI Approved :: BSD License
Classifier: Programming Language :: Python
Classifier: Programming Language :: Python :: 3.7
Classifier: Programming Language :: Python :: 3.8
Classifier: Programming Language :: Python :: 3.9
Classifier: Programming Language :: Python :: 3 :: Only
Classifier: Topic :: Software Development :: Libraries :: Python Modules
Requires-Python: >=3.7
License-File: LICENSE
